Metadata-Version: 1.0
Name: django-shitty-forum
Version: 0.3
Summary: Forum in Django. Don't use it, it sucks.
Home-page: http://github.com/subsume/django-forum
Author: Steve Yeago
Author-email: subsume@gmail.com
License: UNKNOWN
Platform: UNKNOWN
Classifier: Framework :: Django
Classifier: Intended Audience :: Developers
Classifier: Intended Audience :: System Administrators
Classifier: Operating System :: OS Independent
Classifier: Topic :: Software Development
